band_analysis/EG_analysis.py
band_analysis/__init__.py
band_analysis-1.8.dist-info/LICENSE.txt
band_analysis-1.8.dist-info/METADATA
band_analysis-1.8.dist-info/WHEEL
band_analysis-1.8.dist-info/top_level.txt
band_analysis-1.8.dist-info/RECORD
