Metadata-Version: 2.1
Name: band-analysis
Version: 1.8
Summary: Un paquete para analizar bandas de electroforesis
Home-page: https://github.com/esierraj/band_analysis
Author: Egwer David Sierra Jaraba
Classifier: Programming Language :: Python :: 3
Classifier: License :: OSI Approved :: MIT License
License-File: LICENSE.txt
Requires-Dist: numpy ==1.26.4
Requires-Dist: opencv-python
Requires-Dist: pandas
Requires-Dist: scipy
Requires-Dist: matplotlib
